Metadata-Version: 2.1
Name: base1114112
Version: 1.1
Summary: who in the world would use this
Home-page: 
Author: tema5002
Author-email: xtema5002x@gmail.com
License: MIT
Keywords: base1114112
Classifier: Development Status :: 5 - Production/Stable
Classifier: Intended Audience :: Education
Classifier: Operating System :: Microsoft :: Windows :: Windows 11
Classifier: License :: OSI Approved :: MIT License
Classifier: Programming Language :: Python :: 3
